AssimpCy-2.1.1.dist-info/METADATA
AssimpCy-2.1.1.dist-info/RECORD
AssimpCy-2.1.1.dist-info/WHEEL
AssimpCy-2.1.1.dist-info/license.txt
AssimpCy-2.1.1.dist-info/top_level.txt
AssimpCy.libs/libgomp-a34b3233.so.1.0.0
assimpcy/__init__.py
assimpcy/all.cpython-38-x86_64-linux-gnu.so
