Metadata-Version: 2.1
Name: AssimpCy
Version: 2.1.1
Summary: Fast Python bindings for Assimp.
Home-page: https://github.com/jr-garcia/AssimpCy
Author: Javier R. García
License: BSD3
Keywords: 3d,model,geometry,assimp,games,cython
Platform: UNKNOWN
Classifier: Development Status :: 5 - Production/Stable
Classifier: Intended Audience :: Developers
Classifier: License :: OSI Approved :: BSD License
Classifier: Programming Language :: Cython
Classifier: Programming Language :: Python :: 3.7
Classifier: Programming Language :: Python :: 3.8
Classifier: Programming Language :: Python :: 3.9
Classifier: Programming Language :: Python :: 3.10
Classifier: Programming Language :: Python :: Implementation :: CPython
Classifier: Programming Language :: Python :: Implementation :: PyPy
Classifier: Topic :: Games/Entertainment
Classifier: Topic :: Multimedia :: Graphics :: 3D Modeling
Classifier: Topic :: Multimedia :: Graphics :: 3D Rendering
Classifier: Topic :: Software Development :: Libraries
Requires: numpy
License-File: license.txt
Requires-Dist: numpy
